latitude_telemetry/__init__.py
latitude_telemetry/py.typed
latitude_telemetry/env/__init__.py
latitude_telemetry/env/env.py
latitude_telemetry/exporter/__init__.py
latitude_telemetry/exporter/exporter.py
latitude_telemetry/exporter/payloads.py
latitude_telemetry/telemetry/__init__.py
latitude_telemetry/telemetry/telemetry.py
latitude_telemetry/telemetry/types.py
latitude_telemetry/util/__init__.py
latitude_telemetry/util/utils.py
latitude_telemetry-1.0.0.dist-info/METADATA
latitude_telemetry-1.0.0.dist-info/WHEEL
latitude_telemetry-1.0.0.dist-info/RECORD
