Metadata-Version: 2.4
Name: latitude-telemetry
Version: 1.0.0
Summary: Latitude Telemetry for Python
Project-URL: repository, https://github.com/latitude-dev/latitude-llm/tree/main/packages/telemetry/python
Project-URL: homepage, https://github.com/latitude-dev/latitude-llm/tree/main/packages/telemetry/python#readme
Project-URL: documentation, https://github.com/latitude-dev/latitude-llm/tree/main/packages/telemetry/python#readme
Author-email: Latitude Data SL <hello@latitude.so>
Maintainer-email: Latitude Data SL <hello@latitude.so>
License-Expression: LGPL-3.0
Requires-Python: <3.13,>=3.9
Requires-Dist: httpx>=0.27.2
Requires-Dist: openinference-instrumentation-dspy>=0.1.14
Requires-Dist: openinference-instrumentation-litellm>=0.1.6
Requires-Dist: openinference-semantic-conventions>=0.1.12
Requires-Dist: opentelemetry-api>=1.29.0
Requires-Dist: opentelemetry-instrumentation-alephalpha>=0.36.0
Requires-Dist: opentelemetry-instrumentation-anthropic>=0.36.0
Requires-Dist: opentelemetry-instrumentation-bedrock>=0.36.0
Requires-Dist: opentelemetry-instrumentation-cohere>=0.36.0
Requires-Dist: opentelemetry-instrumentation-google-generativeai>=0.36.0
Requires-Dist: opentelemetry-instrumentation-groq>=0.36.0
Requires-Dist: opentelemetry-instrumentation-haystack>=0.36.0
Requires-Dist: opentelemetry-instrumentation-langchain>=0.36.0
Requires-Dist: opentelemetry-instrumentation-llamaindex>=0.36.0
Requires-Dist: opentelemetry-instrumentation-mistralai>=0.36.0
Requires-Dist: opentelemetry-instrumentation-ollama>=0.36.0
Requires-Dist: opentelemetry-instrumentation-openai>=0.36.0
Requires-Dist: opentelemetry-instrumentation-replicate>=0.36.0
Requires-Dist: opentelemetry-instrumentation-sagemaker>=0.36.0
Requires-Dist: opentelemetry-instrumentation-threading>=0.50b0
Requires-Dist: opentelemetry-instrumentation-together>=0.36.0
Requires-Dist: opentelemetry-instrumentation-transformers>=0.36.0
Requires-Dist: opentelemetry-instrumentation-vertexai>=0.36.0
Requires-Dist: opentelemetry-instrumentation-watsonx>=0.36.0
Requires-Dist: opentelemetry-sdk>=1.29.0
Requires-Dist: opentelemetry-semantic-conventions-ai>=0.4.2
Requires-Dist: pydantic>=2.10.3
Requires-Dist: typing-extensions>=4.12.2
